.gitignore
README.rst
allfiles.py
setup.py
allfiles.egg-info/PKG-INFO
allfiles.egg-info/SOURCES.txt
allfiles.egg-info/dependency_links.txt
allfiles.egg-info/top_level.txt