Metadata-Version: 1.1
Name: allfiles
Version: 1.0
Summary: Iterate matched files in directory trees
Home-page: UNKNOWN
Author: OMOTO Kenji
Author-email: doloopwhile@gmail.com
License: MIT
Platform: UNKNOWN
Classifier: Programming Language :: Python :: 3
Classifier: Development Status :: 4 - Beta
Classifier: License :: OSI Approved :: MIT License
